hyperload/__init__.py
hyperload/hyperload.cpython-312-darwin.so
hyperload-0.1.0.dist-info/METADATA
hyperload-0.1.0.dist-info/WHEEL
hyperload-0.1.0.dist-info/licenses/LICENSE
hyperload-0.1.0.dist-info/RECORD
