Metadata-Version: 2.4
Name: hyperload
Version: 0.1.0
Classifier: Development Status :: 4 - Beta
Classifier: Intended Audience :: Developers
Classifier: Intended Audience :: Science/Research
Classifier: License :: OSI Approved :: MIT License
Classifier: Operating System :: OS Independent
Classifier: Programming Language :: Python :: 3
Classifier: Programming Language :: Python :: 3.8
Classifier: Programming Language :: Python :: 3.9
Classifier: Programming Language :: Python :: 3.10
Classifier: Programming Language :: Python :: 3.11
Classifier: Programming Language :: Python :: 3.12
Classifier: Programming Language :: Rust
Classifier: Topic :: Scientific/Engineering
Classifier: Topic :: System :: Distributed Computing
Requires-Dist: pytest>=7.0 ; extra == 'dev'
Requires-Dist: maturin>=1.5 ; extra == 'dev'
Provides-Extra: dev
License-File: LICENSE
Summary: A high-performance distributed data loader powered by Rust. Load files from S3 and local disk with blazing speed.
Keywords: data-loading,s3,async,rust,high-performance,distributed,ml,training
Author-email: Jishnu Duhan <jishnu.s.duhan@gmail.com>
License: MIT
Requires-Python: >=3.8
Project-URL: Documentation, https://github.com/DuhanJishnu/hyperload#readme
Project-URL: Homepage, https://github.com/DuhanJishnu/hyperload
Project-URL: Issues, https://github.com/DuhanJishnu/hyperload/issues
Project-URL: Repository, https://github.com/DuhanJishnu/hyperload
